govtech_csg_xcg/securefileupload/File.py
govtech_csg_xcg/securefileupload/__init__.py
govtech_csg_xcg/securefileupload/decorator.py
govtech_csg_xcg/securefileupload/middleware.py
govtech_csg_xcg/securefileupload/utils.py
govtech_csg_xcg/securefileupload/validators.py
govtech_csg_xcg/securefileupload/conf/__init__.py
govtech_csg_xcg/securefileupload/conf/settings.py
govtech_csg_xcg/securefileupload/data/whitelists.py
govtech_csg_xcg/securefileupload/modules/converter.py
govtech_csg_xcg/securefileupload/modules/evaluator.py
govtech_csg_xcg/securefileupload/modules/helper.py
govtech_csg_xcg/securefileupload/modules/sanitization/__init__.py
govtech_csg_xcg/securefileupload/modules/sanitization/basic.py
govtech_csg_xcg/securefileupload/modules/sanitization/pdf.py
govtech_csg_xcg/securefileupload/modules/sanitization/sanitizer.py
govtech_csg_xcg/securefileupload/modules/validation/__init__.py
govtech_csg_xcg/securefileupload/modules/validation/antivirus.py
govtech_csg_xcg/securefileupload/modules/validation/basic.py
govtech_csg_xcg/securefileupload/modules/validation/image.py
govtech_csg_xcg/securefileupload/modules/validation/quicksand.py
govtech_csg_xcg/securefileupload/modules/validation/validator.py
govtech_csg_xcg/securefileupload/vendor/pdfid/__init__.py
govtech_csg_xcg/securefileupload/vendor/pdfid/__main__.py
govtech_csg_xcg/securefileupload/vendor/pdfid/pdfid.py
govtech_csg_xcg/securefileupload/vendor/yara/test.yar
govtech_csg_xcg_securefileupload-0.1.0.dist-info/LICENSE
govtech_csg_xcg_securefileupload-0.1.0.dist-info/METADATA
govtech_csg_xcg_securefileupload-0.1.0.dist-info/WHEEL
govtech_csg_xcg_securefileupload-0.1.0.dist-info/top_level.txt
govtech_csg_xcg_securefileupload-0.1.0.dist-info/RECORD
