Metadata-Version: 2.1
Name: govtech-csg-xcg-securefileupload
Version: 0.1.0
Summary: XCG middleware to prevent malicious file uploads.
Project-URL: Homepage, https://xcg.tech.gov.sg
Project-URL: Documentation, https://xcg.tech.gov.sg
Project-URL: Repository, https://github.com/GovTech-CSG/govtech-csg-xcg-securefileupload
Classifier: Development Status :: 4 - Beta
Classifier: License :: OSI Approved :: Mozilla Public License 2.0 (MPL 2.0)
Requires-Python: >=3.8
License-File: LICENSE
Requires-Dist: django ~=4.1
Requires-Dist: exifread
Requires-Dist: Pillow
Requires-Dist: clamd
Requires-Dist: python-magic ; platform_system != "Windows"
Requires-Dist: python-magic-bin ==0.4.14 ; platform_system == "Windows"
Provides-Extra: quicksand
Requires-Dist: quicksand ; extra == 'quicksand'
Requires-Dist: yara-python ; (platform_system != "Windows" and platform_system != "Darwin") and extra == 'quicksand'
Requires-Dist: yara-python ==4.2.3 ; (platform_system == "Windows" or platform_system == "Darwin") and extra == 'quicksand'
Provides-Extra: yara
Requires-Dist: yara-python ; (platform_system != "Windows" and platform_system != "Darwin") and extra == 'yara'
Requires-Dist: yara-python ==4.2.3 ; (platform_system == "Windows" or platform_system == "Darwin") and extra == 'yara'
